MANIFEST.in
README.rst
setup.py
tests/__init__.py
tests/test_widgets.py
tw2/__init__.py
tw2.protovis.core.egg-info/PKG-INFO
tw2.protovis.core.egg-info/SOURCES.txt
tw2.protovis.core.egg-info/dependency_links.txt
tw2.protovis.core.egg-info/entry_points.txt
tw2.protovis.core.egg-info/namespace_packages.txt
tw2.protovis.core.egg-info/not-zip-safe
tw2.protovis.core.egg-info/requires.txt
tw2.protovis.core.egg-info/top_level.txt
tw2/protovis/__init__.py
tw2/protovis/core/__init__.py
tw2/protovis/core/defaults.py
tw2/protovis/core/pvobjects.py
tw2/protovis/core/resources.py
tw2/protovis/core/samples.py
tw2/protovis/core/widgets.py
tw2/protovis/core/static/protovis/3.2/.DS_Store
tw2/protovis/core/static/protovis/3.2/LICENSE
tw2/protovis/core/static/protovis/3.2/README
tw2/protovis/core/static/protovis/3.2/protovis.js
tw2/protovis/core/static/protovis/3.2/protovis.min.js
tw2/protovis/core/templates/__init__.py
tw2/protovis/core/templates/mark.mak
tw2/protovis/core/templates/widget.mak