Metadata-Version: 1.1
Name: tw2.protovis.core
Version: 0.2.0
Summary: toscawidgets2 wrapper for the stanford protovis toolkit
Home-page: http://github.com/toscawidgets/tw2.protovis.core
Author: Ralph Bean
Author-email: rbean@redhat.com
License: UNKNOWN
Keywords: toscawidgets.widgets
Platform: UNKNOWN
Classifier: Development Status :: 3 - Alpha
Classifier: Environment :: Web Environment
Classifier: Environment :: Web Environment :: ToscaWidgets
Classifier: Topic :: Software Development :: Libraries :: Python Modules
Classifier: Topic :: Software Development :: Widget Sets
Classifier: Intended Audience :: Developers
Classifier: Operating System :: OS Independent
Classifier: Programming Language :: Python
Classifier: Programming Language :: JavaScript
